{"eloArray":[{"id":15482296,"elo":1120,"name":"ZeeBee"},{"id":14907464,"elo":1096,"name":"RoA | Youngblood"},{"id":14914372,"elo":1077,"name":"jayson"},{"id":14894356,"elo":1076,"name":"TSM | Leffen"},{"id":14861075,"elo":1072,"name":"d4nace"},{"id":14893385,"elo":1071,"name":"GP | I0N"},{"id":14894109,"elo":1071,"name":"DT ELPE | kusi"},{"id":14896631,"elo":1069,"name":"Squinty"},{"id":14893409,"elo":1064,"name":"mow_kitty"},{"id":14893255,"elo":1061,"name":"Lucius"},{"id":15257876,"elo":1059,"name":"Combo Devils | ThundeRzPeiGN"},{"id":14893281,"elo":1057,"name":"Ryan"},{"id":14909245,"elo":1053,"name":"DrLobster"},{"id":14893981,"elo":1050,"name":"LITE | HealsGood"},{"id":14893249,"elo":1049,"name":"SQUAWK! | BioBirb"},{"id":14910458,"elo":1047,"name":"RoA | Etalus"},{"id":14861103,"elo":1046,"name":"PlushyPanic!"},{"id":15069021,"elo":1046,"name":"Mazer | Ralph"},{"id":14893193,"elo":1046,"name":"MSB"},{"id":14893718,"elo":1045,"name":"oshari"},{"id":14900393,"elo":1045,"name":"HF | Nemmy"},{"id":14893795,"elo":1044,"name":"Miss Manners"},{"id":14893840,"elo":1044,"name":"SSG | JUICE"},{"id":14934008,"elo":1035,"name":"Sparx21"},{"id":14909355,"elo":1034,"name":"UGS | Syphir"},{"id":14893203,"elo":1033,"name":"birdup"},{"id":14893970,"elo":1032,"name":"eepy | dreamlamb"},{"id":14899812,"elo":1032,"name":"Dingodial"},{"id":14893161,"elo":1032,"name":"Jut"},{"id":14894285,"elo":1032,"name":"VIBE | HKP"},{"id":14894234,"elo":1032,"name":"Scuttle"},{"id":14907562,"elo":1032,"name":"xRed"},{"id":14893691,"elo":1031,"name":"thezivas"},{"id":14909392,"elo":1031,"name":"Vimber"},{"id":14893152,"elo":1031,"name":"Eleven"},{"id":14893318,"elo":1030,"name":"OoDa"},{"id":14893331,"elo":1030,"name":"bobthebobbo"},{"id":14893197,"elo":1030,"name":"Strawberry Forest"},{"id":14899537,"elo":1030,"name":"doctorbattle"},{"id":15583936,"elo":1029,"name":"alt | Seggo"},{"id":14898004,"elo":1029,"name":"d4nace"},{"id":14893242,"elo":1029,"name":"OhNo | Gorklax"},{"id":14893267,"elo":1029,"name":"Sawstep"},{"id":14893207,"elo":1028,"name":"Haze"},{"id":14900594,"elo":1028,"name":"CakeAssault"},{"id":14903502,"elo":1028,"name":"TruePenguini"},{"id":14893268,"elo":1028,"name":"hibou"},{"id":14895663,"elo":1026,"name":"NE | Lord Bagel"},{"id":14893727,"elo":1026,"name":"Hey | Chompers"},{"id":14936109,"elo":1026,"name":"KD8"},{"id":14893239,"elo":1020,"name":"DT Charm | elkiies"},{"id":14861082,"elo":1019,"name":"DT | Spyker"},{"id":14893489,"elo":1019,"name":"Oneoutkast"},{"id":14893875,"elo":1019,"name":"BRG | T. Richard"},{"id":14893468,"elo":1019,"name":"12th | Spyre"},{"id":14930816,"elo":1019,"name":"Nuzzlyleaf"},{"id":14861095,"elo":1018,"name":"MSB"},{"id":14893804,"elo":1018,"name":"AZ LB! | Refrain"},{"id":14893364,"elo":1018,"name":"Marvelous_Marco"},{"id":14865132,"elo":1017,"name":"Tudle"},{"id":15065829,"elo":1017,"name":"DT Charm | elkiies"},{"id":14895606,"elo":1017,"name":"MG | ex"},{"id":15529932,"elo":1017,"name":"DT MOJO | Wai"},{"id":14893200,"elo":1017,"name":"Penguin"},{"id":14894453,"elo":1017,"name":"ShakeDrizzle"},{"id":14893754,"elo":1017,"name":"Dhir"},{"id":14935091,"elo":1017,"name":"YV | Nocturnal Joey"},{"id":14893794,"elo":1017,"name":"Zane W"},{"id":15234351,"elo":1017,"name":"Flaming Hot Vegitos"},{"id":14912455,"elo":1016,"name":"VIBE | Omar"},{"id":14893300,"elo":1016,"name":"Blane"},{"id":14908560,"elo":1016,"name":"DT | skrupp"},{"id":14903438,"elo":1015,"name":"Zain"},{"id":14904021,"elo":1015,"name":"Gooshi | Veil"},{"id":14893327,"elo":1015,"name":"YHG | Guinness"},{"id":14893310,"elo":1015,"name":"Rymo"},{"id":14895843,"elo":1015,"name":"RoseJ"},{"id":14914404,"elo":1014,"name":"Riven"},{"id":14893388,"elo":1014,"name":"ASINISTERTACO"},{"id":14893505,"elo":1014,"name":"Lucio"},{"id":14893490,"elo":1013,"name":"PlushyPanic!"},{"id":14900347,"elo":1013,"name":"HWC | TapatioJ"},{"id":14861090,"elo":1012,"name":"Zora"},{"id":14861096,"elo":1012,"name":"36th | Dauzen"},{"id":14893829,"elo":1012,"name":"TuesdayTastic"},{"id":14894994,"elo":1004,"name":"river"},{"id":14863104,"elo":1003,"name":"Aztral"},{"id":14900395,"elo":1003,"name":"Skooli"},{"id":14923353,"elo":1003,"name":"HouseOfBlades | CreditKarm"},{"id":14934233,"elo":1003,"name":"Jackie Peanuts"},{"id":14899668,"elo":1003,"name":"Arcain"},{"id":15065843,"elo":1002,"name":"Liquid | Dabuz"},{"id":14893136,"elo":1002,"name":"Wisely"},{"id":14893831,"elo":1002,"name":"geck0"},{"id":14894020,"elo":1002,"name":"bonfire10"},{"id":14893982,"elo":1002,"name":"Spyker"},{"id":14933971,"elo":1002,"name":"CJ"},{"id":14893360,"elo":1002,"name":"SquireLynx"},{"id":14893266,"elo":1002,"name":"SNT | Danzello"},{"id":14906794,"elo":1002,"name":"Popguin"},{"id":14893393,"elo":1002,"name":"SAUL | rubyrosecrowns"},{"id":14893497,"elo":1002,"name":"JeRex"},{"id":14893365,"elo":1002,"name":"Teasports | Robbie0-3"},{"id":14893512,"elo":1002,"name":"SLO | Ramserss"},{"id":14893137,"elo":1001,"name":"Jiggly"},{"id":14894464,"elo":1001,"name":"TAILSEP"},{"id":15367508,"elo":1001,"name":"Dandy"},{"id":14907237,"elo":1001,"name":"Stanky"},{"id":14895198,"elo":1001,"name":"Papyrus"},{"id":14893301,"elo":1001,"name":"Velouria"},{"id":14905013,"elo":1001,"name":"damndaniel"},{"id":15065849,"elo":1000,"name":"LG | MkLeo"},{"id":14895524,"elo":1000,"name":"Strider"},{"id":14897085,"elo":1000,"name":"TemporaryPlan"},{"id":15373904,"elo":999,"name":"White Jack Harlow"},{"id":14894423,"elo":999,"name":"Heys"},{"id":15505947,"elo":999,"name":"Anchor"},{"id":14893906,"elo":999,"name":"Toma_"},{"id":14893159,"elo":999,"name":"TBGG"},{"id":14894516,"elo":989,"name":"Loucan"},{"id":14893861,"elo":989,"name":"Reesch"},{"id":14866838,"elo":988,"name":"Jack Ryan"},{"id":14865938,"elo":987,"name":"AZ LB! | Refrain"},{"id":14896018,"elo":986,"name":"BlackAce"},{"id":14893345,"elo":986,"name":"Bbatts"},{"id":14893262,"elo":986,"name":"Jolt"},{"id":14900672,"elo":986,"name":"HWC | BagtheTea"},{"id":14895797,"elo":986,"name":"T_K_3"},{"id":14936130,"elo":986,"name":"tEy"},{"id":14896035,"elo":986,"name":"Clockwork"},{"id":14893330,"elo":986,"name":"Cygnus"},{"id":14893215,"elo":986,"name":"NorCal | Dauzen"},{"id":15239963,"elo":986,"name":"Hoshi"},{"id":14893816,"elo":986,"name":"Takeshi"},{"id":14893287,"elo":986,"name":"Wernher"},{"id":14893545,"elo":986,"name":"TheViralMelon"},{"id":14893463,"elo":986,"name":"SLOMELEE | Bozion"},{"id":14861099,"elo":985,"name":"CM | Giga"},{"id":15065855,"elo":985,"name":"26R | ApolloKage"},{"id":14893322,"elo":985,"name":"Luckky"},{"id":14893417,"elo":985,"name":"HipInferno"},{"id":14894776,"elo":985,"name":"Stevie Wonderful"},{"id":14893251,"elo":985,"name":"bam9999"},{"id":14895091,"elo":985,"name":"BobNumbers"},{"id":14911763,"elo":985,"name":"trop"},{"id":14866839,"elo":984,"name":"Ateozc"},{"id":14861086,"elo":984,"name":"GRL | Ahntye"},{"id":15076937,"elo":984,"name":"LG EMG | Max Ketchum"},{"id":14893737,"elo":984,"name":"RCS | Timebones"},{"id":14893235,"elo":984,"name":"4Plusko! | Rosebloom"},{"id":14896666,"elo":984,"name":"Shorts"},{"id":14893383,"elo":984,"name":"GP | OriMori"},{"id":14893175,"elo":984,"name":"Kazer"},{"id":14893762,"elo":984,"name":"EDLN | Saltlord"},{"id":14893306,"elo":984,"name":"transgenderstreetlegend"},{"id":14896781,"elo":984,"name":"corpSwag"},{"id":14893188,"elo":984,"name":"CheesyPotato"},{"id":15065847,"elo":983,"name":"GRD | Tarik"},{"id":15076932,"elo":983,"name":"VGBC | わっち(watch)"},{"id":14906458,"elo":983,"name":"Ziggy"},{"id":14893456,"elo":983,"name":"jop"},{"id":14893270,"elo":983,"name":"Ranch Raccoon."},{"id":14903792,"elo":983,"name":"Niah"},{"id":14893452,"elo":983,"name":"EMG | Zen"},{"id":14893391,"elo":983,"name":"llamaboy"},{"id":14894504,"elo":983,"name":"Boatercycle"},{"id":14893140,"elo":972,"name":"bruhgaming15"},{"id":14893342,"elo":972,"name":"meme"},{"id":14908292,"elo":971,"name":"ravyn"},{"id":14930803,"elo":971,"name":"SchuStats | Schu"},{"id":14861108,"elo":970,"name":"DT Charm | elkiies"},{"id":14894336,"elo":970,"name":"URRUEMY"},{"id":14893430,"elo":970,"name":"StaticQuo"},{"id":14894890,"elo":970,"name":"snek"},{"id":14893353,"elo":970,"name":"Game 3"},{"id":14896831,"elo":970,"name":"F!Ve"},{"id":14893416,"elo":970,"name":"Rato"},{"id":14909141,"elo":970,"name":"Monte Kristo"},{"id":14896002,"elo":970,"name":"Decade"},{"id":14893245,"elo":969,"name":"Yep"},{"id":14906846,"elo":969,"name":"beth"},{"id":14893807,"elo":969,"name":"yum bream"},{"id":14907205,"elo":969,"name":"WoodBeard"},{"id":14893775,"elo":969,"name":"TacTac"},{"id":14906746,"elo":969,"name":"ORCA"},{"id":14893259,"elo":969,"name":"TonyG"},{"id":14908692,"elo":969,"name":"Cal"},{"id":14896485,"elo":969,"name":"JoyconBoyz | Jigga"},{"id":14911713,"elo":969,"name":"phobiac"},{"id":14893404,"elo":969,"name":"WolfLinkX"},{"id":14861088,"elo":968,"name":"Breadstick"},{"id":14861091,"elo":968,"name":"Sweet Lou"},{"id":14893374,"elo":968,"name":"Ultra | Russ"},{"id":14893811,"elo":968,"name":"KingKade"},{"id":14893465,"elo":968,"name":"MTEB"},{"id":14936144,"elo":968,"name":"Link69"},{"id":14896912,"elo":968,"name":"boshy"},{"id":14894439,"elo":968,"name":"Dimitrov"},{"id":14894102,"elo":968,"name":"TrueAlpha"},{"id":14893336,"elo":968,"name":"pangea2"},{"id":14895878,"elo":968,"name":"HoP | LimeCharlie"},{"id":14893855,"elo":968,"name":"Rosario"},{"id":14895400,"elo":968,"name":"BlueMagic"},{"id":14903400,"elo":968,"name":"True Neutral | John Neutral"},{"id":14929825,"elo":968,"name":"Mental Djent"},{"id":14893803,"elo":968,"name":"Goyard"},{"id":14893735,"elo":968,"name":"LTH | Sickalaus"},{"id":14861115,"elo":967,"name":"jadon't"},{"id":14893853,"elo":967,"name":"inkdoom"},{"id":14893296,"elo":967,"name":"Heathen"},{"id":14896030,"elo":967,"name":"TAG | mallow"},{"id":14893219,"elo":967,"name":"SuufferPNG"},{"id":14896305,"elo":967,"name":"Mongoose"},{"id":14893246,"elo":967,"name":"Sheepagator"},{"id":14894175,"elo":967,"name":"THUG SHAKER MIND CONTROL"},{"id":14936161,"elo":967,"name":"CommonEnemy"},{"id":14894083,"elo":967,"name":"jett"},{"id":14929639,"elo":966,"name":"UCSD | qwil"},{"id":14936226,"elo":966,"name":"JM140"},{"id":14893216,"elo":966,"name":"Orbital"},{"id":14911155,"elo":966,"name":"BaileyP2SR"},{"id":14896813,"elo":966,"name":"Mario"},{"id":14910490,"elo":966,"name":"Skydra"},{"id":14893298,"elo":956,"name":"Draken"},{"id":14893997,"elo":955,"name":"slurms"},{"id":14897425,"elo":955,"name":"Ghost"},{"id":14906476,"elo":954,"name":"Ateozc"},{"id":14894023,"elo":953,"name":"EspeonValentine"},{"id":14898121,"elo":952,"name":"Dutchman"},{"id":14997799,"elo":952,"name":"Paradygm"}]}